lobster_tools/__init__.py
lobster_tools/_modidx.py
lobster_tools/arctic_cli.py
lobster_tools/config.py
lobster_tools/data_downloading.py
lobster_tools/etf_pipeline_s3.py
lobster_tools/flow_decomposition.py
lobster_tools/preprocessing.py
lobster_tools-0.0.17.dist-info/LICENSE
lobster_tools-0.0.17.dist-info/METADATA
lobster_tools-0.0.17.dist-info/WHEEL
lobster_tools-0.0.17.dist-info/entry_points.txt
lobster_tools-0.0.17.dist-info/top_level.txt
lobster_tools-0.0.17.dist-info/RECORD
