Metadata-Version: 2.1
Name: lobster-tools
Version: 0.0.17
Summary: Python package for working with LOBSTER data, the Nasdaq limit order book data.
Home-page: https://github.com/n-petit/lobster-tools
Author: Nicolas Petit
Author-email: nicolas.petit@keble.ox.ac.uk
License: MIT License
Keywords: LOBSTER LOB nbdev jupyter notebook python
Classifier: Development Status :: 3 - Alpha
Classifier: Intended Audience :: Developers
Classifier: Natural Language :: English
Classifier: Programming Language :: Python :: 3.11
Classifier: License :: OSI Approved :: MIT License
Requires-Python: >=3.11
License-File: LICENSE
Requires-Dist: pandas
Requires-Dist: numpy
Requires-Dist: matplotlib
Requires-Dist: statsmodels
Requires-Dist: scikit-learn
Requires-Dist: click
Requires-Dist: requests
Requires-Dist: hydra-core
Requires-Dist: arcticdb
Requires-Dist: chardet
Provides-Extra: dev
